stupidlogger/__init__.py
stupidlogger/log.py
stupidlogger/loglib.py
stupidlogger-1.0.0.dist-info/METADATA
stupidlogger-1.0.0.dist-info/WHEEL
stupidlogger-1.0.0.dist-info/licenses/LICENSE
stupidlogger-1.0.0.dist-info/RECORD
