Metadata-Version: 2.3
Name: stupidlogger
Version: 1.0.0
Summary: Use `error`, `warn`, `info`, `debug`, `log` like you use `print`
Project-URL: Homepage, https://github.com/inesvar/pythonLogger
Author-email: inesvar <90340779+inesvar@users.noreply.github.com>
License-File: LICENSE
Classifier: License :: OSI Approved :: MIT License
Classifier: Operating System :: OS Independent
Classifier: Programming Language :: Python :: 3
Requires-Python: >=3.10
Requires-Dist: colored>=2.2.0
